face_identification/__init__.py
face_identification/create_face_bank.py
face_identification/face_identification.py
face_identification-1.0.0.dist-info/METADATA
face_identification-1.0.0.dist-info/WHEEL
face_identification-1.0.0.dist-info/top_level.txt
face_identification-1.0.0.dist-info/RECORD
